senseid/__about__.py
senseid/__init__.py
senseid/definitions/.git
senseid/definitions/LICENSE
senseid/definitions/README.md
senseid/definitions/senseid_ble.yaml
senseid/definitions/senseid_rain.yaml
senseid/parsers/__init__.py
senseid/parsers/ble/__init__.py
senseid/parsers/ble/yaml.py
senseid/parsers/rain/__init__.py
senseid/parsers/rain/yaml.py
senseid/readers/__init__.py
senseid/readers/klsblelcr.py
senseid/readers/llrp.py
senseid/readers/nurapi.py
senseid/readers/nurapy.py
senseid/readers/octane.py
senseid/readers/redrcp.py
senseid/readers/scanner/__init__.py
senseid/readers/scanner/multicast_dns_service_discovery.py
senseid/readers/scanner/serialport.py
senseid-0.6.1.dist-info/METADATA
senseid-0.6.1.dist-info/WHEEL
senseid-0.6.1.dist-info/licenses/LICENSE.txt
senseid-0.6.1.dist-info/RECORD
