Metadata-Version: 2.4
Name: senseid
Version: 0.6.1
Project-URL: Documentation, https://github.com/kliskatek/senseid#readme
Project-URL: Issues, https://github.com/kliskatek/senseid/issues
Project-URL: Source, https://github.com/kliskatek/senseid
Author-email: Ibon Zalbide <ibon.zalbide@kliskatek.com>, Aritz Alonso <aritz.alonso@kliskatek.com>
License-Expression: MIT
License-File: LICENSE.txt
Classifier: Development Status :: 4 - Beta
Classifier: Programming Language :: Python
Classifier: Programming Language :: Python :: 3.8
Classifier: Programming Language :: Python :: 3.9
Classifier: Programming Language :: Python :: 3.10
Classifier: Programming Language :: Python :: 3.11
Classifier: Programming Language :: Python :: 3.12
Classifier: Programming Language :: Python :: Implementation :: CPython
Classifier: Programming Language :: Python :: Implementation :: PyPy
Requires-Python: >=3.8
Requires-Dist: dataclasses-json
Requires-Dist: driver-sble-py-klsblelcf
Requires-Dist: nurapi
Requires-Dist: nurapy
Requires-Dist: octane-sdk-wrapper
Requires-Dist: pyyaml
Requires-Dist: redrcp
Requires-Dist: sllurp
Requires-Dist: usb-monitor
Requires-Dist: zeroconf
Provides-Extra: dev
Requires-Dist: pytest; extra == 'dev'
